setup.py
infi/__init__.py
infi.amqp.egg-info/PKG-INFO
infi.amqp.egg-info/SOURCES.txt
infi.amqp.egg-info/dependency_links.txt
infi.amqp.egg-info/entry_points.txt
infi.amqp.egg-info/namespace_packages.txt
infi.amqp.egg-info/requires.txt
infi.amqp.egg-info/top_level.txt
infi/amqp/__init__.py
infi/amqp/__version__.py