Metadata-Version: 1.0
Name: infi.amqp
Version: 1.0
Summary: Simple AMQP publisher and consumer
Home-page: UNKNOWN
Author: Amnon Grossman
Author-email: amnong@gmail.com
License: BSD
Platform: UNKNOWN
Classifier: Intended Audience :: Developers
Classifier: Operating System :: OS Independent
Classifier: Programming Language :: Python
